[
    {
        "기사명": "구글 'AI 스마트 안경' 내년 베일 벗는다",
        "링크": "https://www.etnews.com/20251209000421",
        "년": "2025",
        "월": "12",
        "일": "09",
        "시": "19",
        "분": "58"
    },
    {
        "기사명": "삼성SDI·스텔란티스 합작공장 ESS용 LFP 전환 착수",
        "링크": "https://www.etnews.com/20251209000404",
        "년": "2025",
        "월": "12",
        "일": "09",
        "시": "18",
        "분": "49"
    },
    {
        "기사명": "KT CEO 최종 후보에 박윤영·주형철·홍원표",
        "링크": "https://www.etnews.com/20251209000403",
        "년": "2025",
        "월": "12",
        "일": "09",
        "시": "18",
        "분": "49"
    },
    {
        "기사명": "KAIST, AI로 인간 집단행동 예측하다...세계 최고 학회서 '1위' 성적 거둬",
        "링크": "https://www.etnews.com/20251209000395",
        "년": "2025",
        "월": "12",
        "일": "09",
        "시": "18",
        "분": "36"
    },
    {
        "기사명": "KAIST 교수협, 조속한 차기 총장 선임 촉구",
        "링크": "https://www.etnews.com/20251209000385",
        "년": "2025",
        "월": "12",
        "일": "09",
        "시": "18",
        "분": "24"
    },
    {
        "기사명": "'정보보호산업인의 밤' 개최…배경훈, “연내 2차 정보보호 종합대책 발표”",
        "링크": "https://www.etnews.com/20251209000062",
        "년": "2025",
        "월": "12",
        "일": "09",
        "시": "18",
        "분": "00"
    },
    {
        "기사명": "팀뷰어 “세계 기업 42%, 기술 장애로 매출 손실…AI가 해결책”",
        "링크": "https://www.etnews.com/20251209000370",
        "년": "2025",
        "월": "12",
        "일": "09",
        "시": "17",
        "분": "51"
    },
    {
        "기사명": "사각, '디지털 글로벌화 유공' 과기부장관 표창 수상",
        "링크": "https://www.etnews.com/20251209000369",
        "년": "2025",
        "월": "12",
        "일": "09",
        "시": "17",
        "분": "49"
    },
    {
        "기사명": "전 부처 'AI 평가표' 나온다…중복 투자 방지·소버린 AI 드라이브 포석",
        "링크": "https://www.etnews.com/20251209000201",
        "년": "2025",
        "월": "12",
        "일": "09",
        "시": "17",
        "분": "00"
    },
    {
        "기사명": "직스테크놀로지, 충남대와 산학협력 MOU…국산 CAD·AI 설계 교육 강화",
        "링크": "https://www.etnews.com/20251209000357",
        "년": "2025",
        "월": "12",
        "일": "09",
        "시": "16",
        "분": "56"
    },
    {
        "기사명": "인포보스, 오는 12일 예측형AI 융합 세미나 개최",
        "링크": "https://www.etnews.com/20251209000356",
        "년": "2025",
        "월": "12",
        "일": "09",
        "시": "16",
        "분": "51"
    },
    {
        "기사명": "[에듀플러스]큐피드AI '정시 Pick', 수능 성적표 한 장으로 끝내는 AI 정시 전략 서비스 출시",
        "링크": "https://www.etnews.com/20251209000353",
        "년": "2025",
        "월": "12",
        "일": "09",
        "시": "16",
        "분": "48"
    },
    {
        "기사명": "수원시, R&D사이언스파크 내년1월 도시개발구역 지정…첨단 R&D 허브 본격화",
        "링크": "https://www.etnews.com/20251209000352",
        "년": "2025",
        "월": "12",
        "일": "09",
        "시": "16",
        "분": "42"
    },
    {
        "기사명": "[에듀플러스]숭실대, 'AI·AX 특성화' 본격 추진…4년간 20억 원 투입",
        "링크": "https://www.etnews.com/20251209000349",
        "년": "2025",
        "월": "12",
        "일": "09",
        "시": "16",
        "분": "26"
    },
    {
        "기사명": "[에듀플러스]성균관대 SKK GSB, 'AI Futures 포럼' 성료…글로벌 AI 리더십 입증",
        "링크": "https://www.etnews.com/20251209000346",
        "년": "2025",
        "월": "12",
        "일": "09",
        "시": "16",
        "분": "21"
    },
    {
        "기사명": "[AI와 디지털전환] 안전과 표준화 그리고 규제프리, 피지컬AI 출발점이다",
        "링크": "https://www.etnews.com/20251209000138",
        "년": "2025",
        "월": "12",
        "일": "09",
        "시": "16",
        "분": "00"
    },
    {
        "기사명": "[ET시론] 2000년 만의 반전:점(點)의 재발견이 K사이언스를 세계 과학패권 중심에 세웠다",
        "링크": "https://www.etnews.com/20251209000303",
        "년": "2025",
        "월": "12",
        "일": "09",
        "시": "16",
        "분": "00"
    },
    {
        "기사명": "[人사이트] “AI·주니어 해커 적극 품는 것이 금융 보안 미래” 김태욱 토스증권 시큐리티 리서처",
        "링크": "https://www.etnews.com/20251209000234",
        "년": "2025",
        "월": "12",
        "일": "09",
        "시": "16",
        "분": "00"
    },
    {
        "기사명": "[사설]부처 AI 평가, 목적과 기준에 충실해야",
        "링크": "https://www.etnews.com/20251209000329",
        "년": "2025",
        "월": "12",
        "일": "09",
        "시": "15",
        "분": "51"
    },
    {
        "기사명": "학계, 과방위서 “전력구매 개편 없이 AI 강국 실현 불가”",
        "링크": "https://www.etnews.com/20251209000296",
        "년": "2025",
        "월": "12",
        "일": "09",
        "시": "15",
        "분": "10"
    },
    {
        "기사명": "가비아, ＇인공지능혁신대상＇ 수상 기념...＇AI채팅＇ 첫해 50% 할인",
        "링크": "https://www.etnews.com/20251211000059",
        "년": "2025",
        "월": "12",
        "일": "11",
        "시": "09",
        "분": "49"
    },
    {
        "기사명": "“AI로 산업재해 잡는다”…에스원, 산업 현장 맞춤 안전 솔루션 선봬",
        "링크": "https://www.etnews.com/20251211000056",
        "년": "2025",
        "월": "12",
        "일": "11",
        "시": "09",
        "분": "46"
    },
    {
        "기사명": "웨이센-국제성모병원, 글로벌 의료AI 확산 맞손",
        "링크": "https://www.etnews.com/20251211000055",
        "년": "2025",
        "월": "12",
        "일": "11",
        "시": "09",
        "분": "46"
    },
    {
        "기사명": "클루커스, IPO 주관사로 NH증권·하나증권 선정…“글로벌 AI MSP 도약 본격화”",
        "링크": "https://www.etnews.com/20251211000053",
        "년": "2025",
        "월": "12",
        "일": "11",
        "시": "09",
        "분": "43"
    },
    {
        "기사명": "광주시, ＇광융합·AI＇ 인프라 방위산업으로 확대…산학연 전략회의 개최",
        "링크": "https://www.etnews.com/20251211000042",
        "년": "2025",
        "월": "12",
        "일": "11",
        "시": "09",
        "분": "29"
    },
    {
        "기사명": "AI 시대에 주목할 UX 라이팅 3대 트렌드… 이춘희 UX라이팅랩 대표 “자동화· 역할 확장· 조직차원의 재편”",
        "링크": "https://www.etnews.com/20251211000038",
        "년": "2025",
        "월": "12",
        "일": "11",
        "시": "09",
        "분": "25"
    },
    {
        "기사명": "용인시, 한국ESG대상 지자체 환경·사회·거버넌스 대상 수상",
        "링크": "https://www.etnews.com/20251211000032",
        "년": "2025",
        "월": "12",
        "일": "11",
        "시": "09",
        "분": "19"
    },
    {
        "기사명": "미 국방부, 300만 인력용 AI 플랫폼에 ＇제미나이＇ 첫 채택",
        "링크": "https://www.etnews.com/20251211000007",
        "년": "2025",
        "월": "12",
        "일": "11",
        "시": "07",
        "분": "41"
    },
    {
        "기사명": "中딥시크, 엔비디아 최신칩 밀반입해 새 AI모델 개발",
        "링크": "https://www.etnews.com/20251211000005",
        "년": "2025",
        "월": "12",
        "일": "11",
        "시": "07",
        "분": "37"
    },
    {
        "기사명": "아드반테스트, AI 메모리용 차세대 핸들러 ＇M5241＇공개",
        "링크": "https://www.etnews.com/20251210000244",
        "년": "2025",
        "월": "12",
        "일": "11",
        "시": "06",
        "분": "00"
    },
    {
        "기사명": "양자·AI·반도체 한데 묶는 경기도, ＇포스트 K-반도체＇ 빅픽처 꺼냈다",
        "링크": "https://www.etnews.com/20251210000086",
        "년": "2025",
        "월": "12",
        "일": "11",
        "시": "05",
        "분": "00"
    },
    {
        "기사명": "포티투마루, “지역 AX에 창조경제혁신센터 등 거점기관 역할 필요”",
        "링크": "https://www.etnews.com/20251211000001",
        "년": "2025",
        "월": "12",
        "일": "11",
        "시": "00",
        "분": "06"
    },
    {
        "기사명": "데이터이쿠, 삼성중공업과 조선·해양 혁신 ＇AI 해커톤＇ 성료",
        "링크": "https://www.etnews.com/20251210000459",
        "년": "2025",
        "월": "12",
        "일": "10",
        "시": "23",
        "분": "53"
    },
    {
        "기사명": "틸론, 스냅태그와 비가시성 워터마크 탑재한 VDI 사업화",
        "링크": "https://www.etnews.com/20251210000458",
        "년": "2025",
        "월": "12",
        "일": "10",
        "시": "23",
        "분": "52"
    },
    {
        "기사명": "중견·중소소프트웨어(SW)기업협의회, 2025년 송년의 밤 성료",
        "링크": "https://www.etnews.com/20251210000445",
        "년": "2025",
        "월": "12",
        "일": "10",
        "시": "22",
        "분": "30"
    },
    {
        "기사명": "이한찬 이엠에스 대표, ＇2025 벤처창업진흥 유공포상＇ 중기부 장관상 수상",
        "링크": "https://www.etnews.com/20251210000423",
        "년": "2025",
        "월": "12",
        "일": "10",
        "시": "21",
        "분": "35"
    },
    {
        "기사명": "경과원, 딥테크 스타트업 해외진출 정책 보고서 발간",
        "링크": "https://www.etnews.com/20251210000421",
        "년": "2025",
        "월": "12",
        "일": "10",
        "시": "21",
        "분": "21"
    },
    {
        "기사명": "[대전 K-헬스 유망기업]〈상〉애니그마테크놀로지스, 신뢰성 높인 ＇AI 의료 솔루션＇ 상용화 도전",
        "링크": "https://www.etnews.com/20251210000419",
        "년": "2025",
        "월": "12",
        "일": "10",
        "시": "21",
        "분": "08"
    },
    {
        "기사명": "경남도 ＇인공지능산업 마스터플랜＇ 수립…”제조기업 AI 전환 지원 5배로”",
        "링크": "https://www.etnews.com/20251210000414",
        "년": "2025",
        "월": "12",
        "일": "10",
        "시": "18",
        "분": "22"
    },
    {
        "기사명": "[에듀플러스]이티에듀-잇플, 디지털 교육 사업 협력 강화",
        "링크": "https://www.etnews.com/20251210000405",
        "년": "2025",
        "월": "12",
        "일": "10",
        "시": "17",
        "분": "26"
    },
    {
        "기사명": "로보스타, 산업용 로봇 넘어 반도체·스마트팩토리로 확장",
        "링크": "https://www.etnews.com/20251211000240",
        "년": "2025",
        "월": "12",
        "일": "11",
        "시": "16",
        "분": "00"
    },
    {
        "기사명": "[기고] AI 패권 시대, 과학기술 인재 확보 전략의 성공 조건",
        "링크": "https://www.etnews.com/20251211000195",
        "년": "2025",
        "월": "12",
        "일": "11",
        "시": "16",
        "분": "00"
    },
    {
        "기사명": "[ET시론] 반복되는 ＇연말 택시대란＇…모빌리티 플랫폼의 과제",
        "링크": "https://www.etnews.com/20251211000065",
        "년": "2025",
        "월": "12",
        "일": "11",
        "시": "16",
        "분": "00"
    },
    {
        "기사명": "[21회 스마트금융컨퍼런스]강병준 전자신문 대표, “AI가 금융 규칙 새로 쓴다”",
        "링크": "https://www.etnews.com/20251211000172",
        "년": "2025",
        "월": "12",
        "일": "11",
        "시": "16",
        "분": "00"
    },
    {
        "기사명": "[21회 스마트금융 컨퍼런스]김희태 신용정보원 팀장 “혁신성장금융 지원, AI로 효율성 확보”",
        "링크": "https://www.etnews.com/20251211000318",
        "년": "2025",
        "월": "12",
        "일": "11",
        "시": "16",
        "분": "00"
    },
    {
        "기사명": "[21회 스마트금융컨퍼런스] 김준석 한화생명 AI실장, “라이프 솔루션 AI로 미래형 보험 선도”",
        "링크": "https://www.etnews.com/20251211000159",
        "년": "2025",
        "월": "12",
        "일": "11",
        "시": "16",
        "분": "00"
    },
    {
        "기사명": "[21회 스마트금융컨퍼런스]김태훈 금융위 금융안전과장 “AI시대, 근본적 금융보안 강화 필수”",
        "링크": "https://www.etnews.com/20251211000187",
        "년": "2025",
        "월": "12",
        "일": "11",
        "시": "16",
        "분": "00"
    },
    {
        "기사명": "[5회 스마트금융 대상] 금융위원장상-카카오뱅크 ＇대화형 AI 서비스＇",
        "링크": "https://www.etnews.com/20251211000142",
        "년": "2025",
        "월": "12",
        "일": "11",
        "시": "16",
        "분": "00"
    },
    {
        "기사명": "[최은수의 AI와 뉴비즈] 〈31〉AI 기술 신화의 종언···이제 비즈니스 모델이 승부 가른다",
        "링크": "https://www.etnews.com/20251211000031",
        "년": "2025",
        "월": "12",
        "일": "11",
        "시": "16",
        "분": "00"
    },
    {
        "기사명": "합격한 자소서 보니 ＇기획·협업·관리＇ 키워드 부상…AI 시대 인간 역량 강조",
        "링크": "https://www.etnews.com/20251211000247",
        "년": "2025",
        "월": "12",
        "일": "11",
        "시": "16",
        "분": "00"
    },
    {
        "기사명": "[GEF 스타트업 이야기] 〈76〉“너는 너무 예민해, 너무 눈치 없어”:AI 너는 괜찮네!",
        "링크": "https://www.etnews.com/20251211000206",
        "년": "2025",
        "월": "12",
        "일": "11",
        "시": "16",
        "분": "00"
    },
    {
        "기사명": "[정구민의 테크읽기] 모빌리티 지식재산권과 불공정무역행위 조사제도",
        "링크": "https://www.etnews.com/20251211000048",
        "년": "2025",
        "월": "12",
        "일": "11",
        "시": "16",
        "분": "00"
    },
    {
        "기사명": "[21회 스마트금융 컨퍼런스] 최용민 우리금융 AI전략센터장 “AI 네이티브 조직으로 대전환”",
        "링크": "https://www.etnews.com/20251211000279",
        "년": "2025",
        "월": "12",
        "일": "11",
        "시": "16",
        "분": "00"
    },
    {
        "기사명": "[21회 스마트금융컨퍼런스]권대영 금융위원회 부위원장 “AI, 금융 게임체인저 될 것”",
        "링크": "https://www.etnews.com/20251211000170",
        "년": "2025",
        "월": "12",
        "일": "11",
        "시": "16",
        "분": "00"
    },
    {
        "기사명": "[21회 스마트금융컨퍼런스] 김규빈 토스증권 대표 “공시·어닝콜·뉴스까지…AI로 투자 여정 돕는다”",
        "링크": "https://www.etnews.com/20251211000238",
        "년": "2025",
        "월": "12",
        "일": "11",
        "시": "16",
        "분": "00"
    },
    {
        "기사명": "[5회 스마트금융 대상]KB銀·카뱅 금융위원장상…“스마트금융으로 고객 접근성 확대”",
        "링크": "https://www.etnews.com/20251211000154",
        "년": "2025",
        "월": "12",
        "일": "11",
        "시": "16",
        "분": "00"
    },
    {
        "기사명": "[5회 스마트금융 대상] 금융위원장상-KB국민은행 ＇KB 화상상담 서비스＇",
        "링크": "https://www.etnews.com/20251211000135",
        "년": "2025",
        "월": "12",
        "일": "11",
        "시": "16",
        "분": "00"
    },
    {
        "기사명": "[차세대 반도체, 경기기업이 키운다]〈④·끝〉칩 세는 로봇부터 배터리 심장까지…테크밸리, X레이로 ＇속내＇ 밝혀",
        "링크": "https://www.etnews.com/20251211000248",
        "년": "2025",
        "월": "12",
        "일": "11",
        "시": "15",
        "분": "27"
    },
    {
        "기사명": "리가켐바이오, 옥찬영 루닛 전 CMO 중개연구 센터장으로 영입",
        "링크": "https://www.etnews.com/20251211000366",
        "년": "2025",
        "월": "12",
        "일": "11",
        "시": "15",
        "분": "19"
    },
    {
        "기사명": "정부, 내년 성장률 1.8%+α…한국형 국부펀드 설립",
        "링크": "https://www.etnews.com/20251211000357",
        "년": "2025",
        "월": "12",
        "일": "11",
        "시": "15",
        "분": "08"
    },
    {
        "기사명": "애니파이브, 베트남 톤득탕대·한전 전력연구원과 ＇신재생 에너지 통합 AI 플랫폼＇ 개발 협력",
        "링크": "https://www.etnews.com/20251211000294",
        "년": "2025",
        "월": "12",
        "일": "12",
        "시": "01",
        "분": "11"
    },
    {
        "기사명": "농진청 “AI로 더 커가는 농업”…새해 업무계획 발표",
        "링크": "https://www.etnews.com/20251211000472",
        "년": "2025",
        "월": "12",
        "일": "11",
        "시": "20",
        "분": "09"
    },
    {
        "기사명": "KT, 2026학년도 수능만점자 축하…광주서석고와 자매결연·AI역량 강화",
        "링크": "https://www.etnews.com/20251211000471",
        "년": "2025",
        "월": "12",
        "일": "11",
        "시": "20",
        "분": "05"
    },
    {
        "기사명": "농식품부, 새해 농정 방향 발표…5대 중점과제·3대 개혁과제 제시",
        "링크": "https://www.etnews.com/20251211000470",
        "년": "2025",
        "월": "12",
        "일": "11",
        "시": "19",
        "분": "59"
    },
    {
        "기사명": "서울시, 지방정부 최초 생성형 AI 기반 통합보안관제 구축",
        "링크": "https://www.etnews.com/20251211000276",
        "년": "2025",
        "월": "12",
        "일": "11",
        "시": "19",
        "분": "00"
    },
    {
        "기사명": "노동부, 노동시간 줄이고 중대재해 사업장 제재...2026년 업무보고",
        "링크": "https://www.etnews.com/20251211000469",
        "년": "2025",
        "월": "12",
        "일": "11",
        "시": "18",
        "분": "49"
    },
    {
        "기사명": "오비고, ＇글로벌 모빌리티 라이프 AX 플랫폼＇ 도약",
        "링크": "https://www.etnews.com/20251211000466",
        "년": "2025",
        "월": "12",
        "일": "11",
        "시": "18",
        "분": "39"
    },
    {
        "기사명": "삼성전자 노사, 2026년 임금교섭 상견례…16일 본교섭",
        "링크": "https://www.etnews.com/20251211000465",
        "년": "2025",
        "월": "12",
        "일": "11",
        "시": "18",
        "분": "39"
    },
    {
        "기사명": "[21회 스마트금융컨퍼런스] “정부 주도 AI 시장 참전이 ＇버블＇ 키운다…개입 지양해야”",
        "링크": "https://www.etnews.com/20251211000440",
        "년": "2025",
        "월": "12",
        "일": "11",
        "시": "18",
        "분": "30"
    },
    {
        "기사명": "美, AI 에이전트 국제표준 주도 시동…오픈AI·앤트로픽 동참",
        "링크": "https://www.etnews.com/20251211000462",
        "년": "2025",
        "월": "12",
        "일": "11",
        "시": "18",
        "분": "23"
    },
    {
        "기사명": "클라우드 네이티브 전환 완료 또는 절반 이상 진행, 18.4%에 그쳐",
        "링크": "https://www.etnews.com/20251211000461",
        "년": "2025",
        "월": "12",
        "일": "11",
        "시": "18",
        "분": "12"
    },
    {
        "기사명": "[에듀플러스]“한국AI서비스학회 첫 전국대회…고교생 ＇AI 창업＇이 현실로”",
        "링크": "https://www.etnews.com/20251211000460",
        "년": "2025",
        "월": "12",
        "일": "11",
        "시": "18",
        "분": "06"
    },
    {
        "기사명": "KAIST, 과기원 첫 AI 단과대학 설립...AI 핵심 인재 양성",
        "링크": "https://www.etnews.com/20251211000210",
        "년": "2025",
        "월": "12",
        "일": "11",
        "시": "18",
        "분": "00"
    },
    {
        "기사명": "메가존클라우드, 동아대 G-LAMP 사업단과 양자·원자 과학 연구 기반 연구 협력",
        "링크": "https://www.etnews.com/20251211000457",
        "년": "2025",
        "월": "12",
        "일": "11",
        "시": "17",
        "분": "58"
    },
    {
        "기사명": "충남-KT, ＇통합 클라우드 네이티브 구축＇ 성과 공주시 등 15개 시군과 공유",
        "링크": "https://www.etnews.com/20251211000454",
        "년": "2025",
        "월": "12",
        "일": "11",
        "시": "17",
        "분": "31"
    },
    {
        "기사명": "[자율주행과 모빌리티]모빌리티 넘어 방산·로봇까지…K센서 고도화",
        "링크": "https://www.etnews.com/20251211000362",
        "년": "2025",
        "월": "12",
        "일": "11",
        "시": "17",
        "분": "30"
    },
    {
        "기사명": "[자율주행과 모빌리티] “＇피지컬 AI＇가 자율주행 레벨4 상용화 핵심”",
        "링크": "https://www.etnews.com/20251211000314",
        "년": "2025",
        "월": "12",
        "일": "11",
        "시": "17",
        "분": "30"
    },
    {
        "기사명": "[자율주행과 모빌리티]전문가들 “유연한 규제가 모빌리티 경쟁력 좌우”",
        "링크": "https://www.etnews.com/20251211000416",
        "년": "2025",
        "월": "12",
        "일": "11",
        "시": "17",
        "분": "30"
    },
    {
        "기사명": "딥노이드-JPI 헬스케어, 글로벌 사업 협력 MOU 체결",
        "링크": "https://www.etnews.com/20251211000433",
        "년": "2025",
        "월": "12",
        "일": "11",
        "시": "16",
        "분": "54"
    },
    {
        "기사명": "[사설] 150조 국민성장펀드에 거는 기대",
        "링크": "https://www.etnews.com/20251211000313",
        "년": "2025",
        "월": "12",
        "일": "11",
        "시": "16",
        "분": "34"
    },
    {
        "기사명": "더존비즈온, 한국AI서비스학회 창립 학술대회서 ＇최우수논문상＇ 수상",
        "링크": "https://www.etnews.com/20251212000338",
        "년": "2025",
        "월": "12",
        "일": "12",
        "시": "17",
        "분": "25"
    },
    {
        "기사명": "NIA-경과원, 판교 스타트업 대상 AI 윤리 문화 조성 추진",
        "링크": "https://www.etnews.com/20251212000327",
        "년": "2025",
        "월": "12",
        "일": "12",
        "시": "16",
        "분": "38"
    },
    {
        "기사명": "경과원, 중소기업 제품디자인 지원사업 성과공유회 개최",
        "링크": "https://www.etnews.com/20251212000322",
        "년": "2025",
        "월": "12",
        "일": "12",
        "시": "16",
        "분": "26"
    },
    {
        "기사명": "전북 디지털배움터, 도민 5만 명 교육…AI 중심 체계로 확장",
        "링크": "https://www.etnews.com/20251212000305",
        "년": "2025",
        "월": "12",
        "일": "12",
        "시": "15",
        "분": "40"
    },
    {
        "기사명": "광주시, RISE 사업 확대…총 48억원 3개 단위과제 참여대학 추가 공모",
        "링크": "https://www.etnews.com/20251212000301",
        "년": "2025",
        "월": "12",
        "일": "12",
        "시": "15",
        "분": "30"
    },
    {
        "기사명": "AI 시장·여론 분석기업 마테크랩 공식 출범… AI 리서치 플랫폼 개발 본격화",
        "링크": "https://www.etnews.com/20251212000297",
        "년": "2025",
        "월": "12",
        "일": "12",
        "시": "15",
        "분": "25"
    },
    {
        "기사명": "네이버클라우드, 코스포와 독자 AI 모델 기반 AX 스타트업 육성",
        "링크": "https://www.etnews.com/20251212000291",
        "년": "2025",
        "월": "12",
        "일": "12",
        "시": "15",
        "분": "16"
    },
    {
        "기사명": "몰로코, AI 광고 솔루션 성과로 국무총리·중기부 표창",
        "링크": "https://www.etnews.com/20251212000289",
        "년": "2025",
        "월": "12",
        "일": "12",
        "시": "15",
        "분": "16"
    },
    {
        "기사명": "솔트룩스, 케이이노텍과 제조분야 AI 확산·DX 이끈다",
        "링크": "https://www.etnews.com/20251212000288",
        "년": "2025",
        "월": "12",
        "일": "12",
        "시": "15",
        "분": "15"
    },
    {
        "기사명": "AI 미술 큐레이션 플랫폼 아르투, 작품 결제에 스테이블코인 적용",
        "링크": "https://www.etnews.com/20251212000285",
        "년": "2025",
        "월": "12",
        "일": "12",
        "시": "15",
        "분": "14"
    },
    {
        "기사명": "워트인텔리전스, 딥엘과 특허 분야 업무 협약 체결",
        "링크": "https://www.etnews.com/20251212000282",
        "년": "2025",
        "월": "12",
        "일": "12",
        "시": "15",
        "분": "11"
    },
    {
        "기사명": "NIA-행안부-오픈데이터포럼, 공공데이터 개방 전략 논의 장 열어",
        "링크": "https://www.etnews.com/20251212000281",
        "년": "2025",
        "월": "12",
        "일": "12",
        "시": "15",
        "분": "11"
    },
    {
        "기사명": "[에듀플러스]데이원컴퍼니 콜로소, ＇2025 디지털 광고 대상＇ 글로벌 캠페인 부문 수상",
        "링크": "https://www.etnews.com/20251212000272",
        "년": "2025",
        "월": "12",
        "일": "12",
        "시": "15",
        "분": "02"
    },
    {
        "기사명": "AX 싱크 탱크 ＇충남 AI 특위＇ 첫 회동…1.5조 AI 국가사업 등 추진 방안 논의",
        "링크": "https://www.etnews.com/20251212000158",
        "년": "2025",
        "월": "12",
        "일": "12",
        "시": "15",
        "분": "00"
    },
    {
        "기사명": "[에듀플러스]동아출판, ＇2025 부산국제아동도서전＇ 참가",
        "링크": "https://www.etnews.com/20251212000268",
        "년": "2025",
        "월": "12",
        "일": "12",
        "시": "14",
        "분": "57"
    },
    {
        "기사명": "개보위, 내년 업무계획 보고…“중대위반에 ＇매출 최대 10%＇ 징벌적과징금”",
        "링크": "https://www.etnews.com/20251212000267",
        "년": "2025",
        "월": "12",
        "일": "12",
        "시": "14",
        "분": "57"
    },
    {
        "기사명": "김혁 SKB 부사장 “콘텐츠·플랫폼 협력 없인 시장 붕괴”…＇IPTV의 날＇",
        "링크": "https://www.etnews.com/20251212000262",
        "년": "2025",
        "월": "12",
        "일": "12",
        "시": "14",
        "분": "45"
    },
    {
        "기사명": "오션스바이오, ＇2025 벤처창업진흥 유공 포상＇ 국무총리상 수상",
        "링크": "https://www.etnews.com/20251212000236",
        "년": "2025",
        "월": "12",
        "일": "12",
        "시": "14",
        "분": "21"
    },
    {
        "기사명": "제이엘케이, 한림대 성심병원에 의료 AI 솔루션 4종 공급",
        "링크": "https://www.etnews.com/20251212000231",
        "년": "2025",
        "월": "12",
        "일": "12",
        "시": "14",
        "분": "15"
    },
    {
        "기사명": "방미통위 “안전·활력 국민 중심”…미디어 생태계 개편 시동",
        "링크": "https://www.etnews.com/20251212000222",
        "년": "2025",
        "월": "12",
        "일": "12",
        "시": "14",
        "분": "01"
    },
    {
        "기사명": "KOIIA 송년의 밤 개최… “기관 창립 10년 및 회원사 지원 확대 발표”",
        "링크": "https://www.etnews.com/20251212000347",
        "년": "2025",
        "월": "12",
        "일": "12",
        "시": "18",
        "분": "12"
    },
    {
        "기사명": "인제대 ＇AI 미래전략 공동세미나＇ 개최…지산학 미래전략 논의",
        "링크": "https://www.etnews.com/20251212000344",
        "년": "2025",
        "월": "12",
        "일": "12",
        "시": "17",
        "분": "43"
    },
    {
        "기사명": "교육부, 맞춤형 학습 위한 ＇K교육 AI＇ 개발 추진",
        "링크": "https://www.etnews.com/20251212000354",
        "년": "2025",
        "월": "12",
        "일": "12",
        "시": "19",
        "분": "47"
    },
    {
        "기사명": "새만금개발청, 내년 RE100산단 등 ＇지산지소형 산업 혁신 생태계＇ 구축",
        "링크": "https://www.etnews.com/20251212000353",
        "년": "2025",
        "월": "12",
        "일": "12",
        "시": "19",
        "분": "11"
    },
    {
        "기사명": "“8명의 AI 리더가 세계를 바꿨다”...타임 ＇올해의 인물＇ 전부 AI 거물들로 도배",
        "링크": "https://www.etnews.com/20251213000007",
        "년": "2025",
        "월": "12",
        "일": "13",
        "시": "11",
        "분": "00"
    },
    {
        "기사명": "우즈베키스탄 좀보이 지역 대표단, ＇뉴럴디＇ 방문…AI 기반 ADS로 전력·인프라 점검진단 협력 확대",
        "링크": "https://www.etnews.com/20251213000012",
        "년": "2025",
        "월": "12",
        "일": "13",
        "시": "14",
        "분": "48"
    },
    {
        "기사명": "SK브로드밴드, ＇AI 업무 파트너＇ 전사 개방…“일하는 방식 혁신”",
        "링크": "https://www.etnews.com/20251212000247",
        "년": "2025",
        "월": "12",
        "일": "14",
        "시": "02",
        "분": "26"
    },
    {
        "기사명": "AI 만나 날개 단 수원시, 경제자유구역 향해 ＇바이오 질주＇",
        "링크": "https://www.etnews.com/20251213000033",
        "년": "2025",
        "월": "12",
        "일": "13",
        "시": "23",
        "분": "07"
    },
    {
        "기사명": "피씨엔(PCN), 가상공간 ＇분위기＇ 읽는 XR AI 개발",
        "링크": "https://www.etnews.com/20251213000031",
        "년": "2025",
        "월": "12",
        "일": "13",
        "시": "22",
        "분": "41"
    },
    {
        "기사명": "국회 ＇AI 헬스케어포럼＇ 출범, 보건의료 기술 제도 기반 논의",
        "링크": "https://www.etnews.com/20251213000025",
        "년": "2025",
        "월": "12",
        "일": "13",
        "시": "20",
        "분": "39"
    },
    {
        "기사명": "“우주가 곧 증시로 내려온다”…스페이스X ＇기업가치 1천200조원＇ 내년 상장 추진",
        "링크": "https://www.etnews.com/20251213000021",
        "년": "2025",
        "월": "12",
        "일": "13",
        "시": "18",
        "분": "44"
    },
    {
        "기사명": "정용진, 美 밴스 부통령 성탄절 만찬 참석…백악관 과학정책실장 면담",
        "링크": "https://www.etnews.com/20251214000035",
        "년": "2025",
        "월": "12",
        "일": "14",
        "시": "09",
        "분": "49"
    },
    {
        "기사명": "[이슈플러스] KT CEO 후보 집중탐구",
        "링크": "https://www.etnews.com/20251212000266",
        "년": "2025",
        "월": "12",
        "일": "14",
        "시": "09",
        "분": "32"
    },
    {
        "기사명": "“이 게임 하면 치매 예방?”... 판치는 ＇AI 가짜 광고＇, 국내 역차별 막고 집행력 확보 시급",
        "링크": "https://www.etnews.com/20251214000024",
        "년": "2025",
        "월": "12",
        "일": "14",
        "시": "09",
        "분": "19"
    },
    {
        "기사명": "인텔, AI PC용 프로세서 주도권 ＇굳히기＇ 나선다",
        "링크": "https://www.etnews.com/20251212000170",
        "년": "2025",
        "월": "12",
        "일": "14",
        "시": "09",
        "분": "00"
    },
    {
        "기사명": "드론·반도체에 ＇창업＇ 더한다…김경희 이천시장, 청년 비전",
        "링크": "https://www.etnews.com/20251214000018",
        "년": "2025",
        "월": "12",
        "일": "14",
        "시": "08",
        "분": "46"
    },
    {
        "기사명": "광주시, ＇국립치의학연구원 유치＇ 결의…치의학산업 선도",
        "링크": "https://www.etnews.com/20251214000046",
        "년": "2025",
        "월": "12",
        "일": "14",
        "시": "10",
        "분": "31"
    },
    {
        "기사명": "LG전자, 서울대와 손잡고 ＇AI 보안 연구센터＇ 설립",
        "링크": "https://www.etnews.com/20251214000047",
        "년": "2025",
        "월": "12",
        "일": "14",
        "시": "10",
        "분": "35"
    }
]